locli/__init__.py
locli/locli.py
locli-0.4.0.dist-info/entry_points.txt
locli-0.4.0.dist-info/WHEEL
locli-0.4.0.dist-info/METADATA
locli-0.4.0.dist-info/RECORD
