Metadata-Version: 2.1
Name: locli
Version: 0.4.0
Summary: 
Author: wonjae.h
Author-email: warren@telelian.com
Requires-Python: >=3.9,<4.0
Classifier: Programming Language :: Python :: 3
Classifier: Programming Language :: Python :: 3.10
Classifier: Programming Language :: Python :: 3.9
Requires-Dist: hiredis (>=2.0.0,<3.0.0)
Requires-Dist: redis (>=4.1.4,<5.0.0)
